{
  "local-dialogposition": {
    "dialog-setting": {
      "height": 821,
      "left": 128,
      "top": 45,
      "width": 1280
    }
  },
  "local-fileposition": {
    "20200812220555-lj3enxa": {
      "endId": "20240508001403-j8ceveg",
      "focusEnd": 1,
      "focusId": "20240508000057-x1ale7e",
      "focusStart": 1,
      "rootId": "20200812220555-lj3enxa",
      "scrollTop": 0,
      "startId": "20210528115012-vst5lwt"
    },
    "20200922102318-oz84yu3": {
      "endId": "20221114172704-ke0r60p",
      "focusEnd": 0,
      "focusId": "20230418093311-dtukze4",
      "focusStart": 0,
      "rootId": "20200922102318-oz84yu3",
      "scrollTop": 0,
      "startId": "20230418093311-dtukze4"
    },
    "20241124182833-kovwzpx": {
      "endId": "20241217090025-ad1w79k",
      "focusEnd": 0,
      "focusId": "20241217090025-ad1w79k",
      "focusStart": 0,
      "rootId": "20241124182833-kovwzpx",
      "scrollTop": 0,
      "startId": "20241124182941-nmmz0rj"
    },
    "20241124182854-cl3o241": {
      "endId": "20241124182854-h00bigm",
      "rootId": "20241124182854-cl3o241",
      "scrollTop": 0,
      "startId": "20241124182854-h00bigm"
    },
    "20241124183048-jaxuhn5": {
      "endId": "20250107163043-widrr47",
      "rootId": "20241124183048-jaxuhn5",
      "scrollTop": 104,
      "startId": "20241124183807-ddcid3g"
    },
    "20241124183550-gcgis65": {
      "endId": "20250106095713-bbrwnjb",
      "focusEnd": 0,
      "focusId": "20250106095713-bbrwnjb",
      "focusStart": 0,
      "rootId": "20241124183550-gcgis65",
      "scrollTop": 0,
      "startId": "20241124193032-3rl23h3"
    },
    "20241217093623-ezy8c9z": {
      "endId": "20241217131041-ceqd6xh",
      "focusEnd": 0,
      "focusId": "20241217093623-nmh7wzd",
      "focusStart": 0,
      "rootId": "20241217093623-ezy8c9z",
      "scrollTop": 0,
      "startId": "20241217093623-nmh7wzd"
    },
    "20241217192701-cexlgme": {
      "endId": "20241223131310-wv1yeke",
      "focusEnd": 4,
      "focusId": "20241217192732-bdvbh15",
      "focusStart": 4,
      "rootId": "20241217192701-cexlgme",
      "scrollTop": 0,
      "startId": "20241217192701-o5j6npn"
    },
    "20241217195007-8gznpvu": {
      "endId": "20250108182732-cr8wrez",
      "focusEnd": 0,
      "focusId": "20241217195007-89xxqh6",
      "focusStart": 0,
      "rootId": "20241217195007-8gznpvu",
      "scrollTop": 1752,
      "startId": "20241217195007-89xxqh6"
    },
    "20241219084837-puu4j2k": {
      "endId": "20241219084901-o0skwjq",
      "focusEnd": 42,
      "focusId": "20241219151131-9te70xh",
      "focusStart": 42,
      "rootId": "20241219084837-puu4j2k",
      "scrollTop": 0,
      "startId": "20241219084837-z27ulj8"
    },
    "20241220095223-avm56hc": {
      "endId": "20241220095410-pamj44i",
      "focusEnd": 0,
      "focusId": "20241220095410-pamj44i",
      "focusStart": 0,
      "rootId": "20241220095223-avm56hc",
      "scrollTop": 0,
      "startId": "20241220095230-hfizehx"
    },
    "20241220132321-spklfse": {
      "endId": "20241220132441-sj8dfa9",
      "focusEnd": 4,
      "focusId": "20241220163448-l8xa5e9",
      "focusStart": 4,
      "rootId": "20241220132321-spklfse",
      "scrollTop": 0,
      "startId": "20241220132321-9g2riwi"
    },
    "20241220170504-0ysa1ty": {
      "endId": "20241221105610-x1slstf",
      "focusEnd": 4,
      "focusId": "20241221110715-o3wp95z",
      "focusStart": 4,
      "rootId": "20241220170504-0ysa1ty",
      "scrollTop": 300,
      "startId": "20241220170504-jccnv22"
    },
    "20241221112345-khmx0ws": {
      "endId": "20250115184608-1f87uol",
      "rootId": "20241221112345-khmx0ws",
      "scrollTop": 0,
      "startId": "20241221112345-k5w157z"
    },
    "20241223142148-8e6okn3": {
      "endId": "20241227141103-rlhdsez",
      "focusEnd": 0,
      "focusId": "20241226210747-7hytrau",
      "focusStart": 0,
      "rootId": "20241223142148-8e6okn3",
      "scrollTop": 300,
      "startId": "20241223142148-r2cmww9"
    },
    "20241223142222-j8jlyqo": {
      "endId": "20250217161351-pxjy55x",
      "focusEnd": 0,
      "focusId": "20250217161351-pxjy55x",
      "focusStart": 0,
      "rootId": "20241223142222-j8jlyqo",
      "scrollTop": 1199,
      "startId": "20241223142222-1wu2try"
    },
    "20241223162649-w3iew6g": {
      "endId": "20250121185541-adhu253",
      "focusEnd": 0,
      "focusId": "20250117161151-77nhucj",
      "focusStart": 0,
      "rootId": "20241223162649-w3iew6g",
      "scrollTop": 700,
      "startId": "20241223162649-7ut9imz"
    },
    "20241224131451-nieztbn": {
      "endId": "20241224131739-l1sax29",
      "focusEnd": 15,
      "focusId": "20241224131659-g4de5hh",
      "focusStart": 15,
      "rootId": "20241224131451-nieztbn",
      "scrollTop": 0,
      "startId": "20241224131451-qft8nzc"
    },
    "20241224161922-vbxmsty": {
      "endId": "20241224162021-ofykbsl",
      "rootId": "20241224161922-vbxmsty",
      "scrollTop": 0,
      "startId": "20241224162003-s1vqtvv"
    },
    "20241225140901-3jttumd": {
      "endId": "20250116130816-64ahtc5",
      "focusEnd": 2,
      "focusId": "20250102131255-h9hg6y5",
      "focusStart": 2,
      "rootId": "20241225140901-3jttumd",
      "scrollTop": 0,
      "startId": "20241225140901-8taxo9d"
    },
    "20241227083613-q7dcu85": {
      "endId": "20241227083642-rp9pav2",
      "focusEnd": 0,
      "focusId": "20241227083642-rp9pav2",
      "focusStart": 0,
      "rootId": "20241227083613-q7dcu85",
      "scrollTop": 0,
      "startId": "20241227083613-txkx08e"
    },
    "20241227151941-qpd0ton": {
      "endId": "20250102162619-y9pm6cz",
      "focusEnd": 9,
      "focusId": "20250102162820-rmz62tm",
      "focusStart": 9,
      "rootId": "20241227151941-qpd0ton",
      "scrollTop": 0,
      "startId": "20241227151941-1utnf4m"
    },
    "20241227160704-en3zv5f": {
      "endId": "20241227162227-mf5y5mk",
      "focusEnd": 469,
      "focusId": "20241227160737-y6nwem0",
      "focusStart": 469,
      "rootId": "20241227160704-en3zv5f",
      "scrollTop": 1272,
      "startId": "20241227160737-y6nwem0"
    },
    "20241228000549-c4okrjp": {
      "endId": "20241228000549-dkxtflw",
      "focusEnd": 0,
      "focusId": "20241228000549-dkxtflw",
      "focusStart": 0,
      "rootId": "20241228000549-c4okrjp",
      "scrollTop": 0,
      "startId": "20241228000549-dkxtflw"
    },
    "20241231133851-vrv8tdm": {
      "endId": "20241231134050-ofvtojt",
      "focusEnd": 0,
      "focusId": "20241231134050-ofvtojt",
      "focusStart": 0,
      "rootId": "20241231133851-vrv8tdm",
      "scrollTop": 80,
      "startId": "20241231133913-2r9ka2e"
    },
    "20241231141357-meb5hmj": {
      "endId": "20241231141357-auglidd",
      "focusEnd": 0,
      "focusId": "20241231141357-auglidd",
      "focusStart": 0,
      "rootId": "20241231141357-meb5hmj",
      "scrollTop": 0,
      "startId": "20241231141357-auglidd"
    },
    "20250106141944-3wixivd": {
      "endId": "20250126205916-4ncopdq",
      "focusEnd": 14,
      "focusId": "20250201092941-i95iqgh",
      "focusStart": 14,
      "rootId": "20250106141944-3wixivd",
      "scrollTop": 0,
      "startId": "20250106141944-4i4ez6b"
    },
    "20250109085853-k0sjoen": {
      "endId": "20250110130534-u5mrcmh",
      "focusEnd": 9,
      "focusId": "20250116171052-6j62g02",
      "focusStart": 9,
      "rootId": "20250109085853-k0sjoen",
      "scrollTop": 0,
      "startId": "20250109085853-zirm9tb"
    },
    "20250110135850-i70fbgv": {
      "endId": "20250113104059-6q7wje1",
      "focusEnd": 14,
      "focusId": "20250113094812-lmkymot",
      "focusStart": 14,
      "rootId": "20250110135850-i70fbgv",
      "scrollTop": 0,
      "startId": "20250110135850-hys329x"
    },
    "20250110140224-agewjci": {
      "endId": "20250110140224-arr4o3z",
      "focusEnd": 0,
      "focusId": "20250110140224-arr4o3z",
      "focusStart": 0,
      "rootId": "20250110140224-agewjci",
      "scrollTop": 0,
      "startId": "20250110140224-arr4o3z"
    },
    "20250110141432-8vwcep7": {
      "endId": "20250110141544-ph9afj3",
      "focusEnd": 43,
      "focusId": "20250110141508-knno4dh",
      "focusStart": 43,
      "rootId": "20250110141432-8vwcep7",
      "scrollTop": 0,
      "startId": "20250110141432-an7tey2"
    },
    "20250113101920-gt8wt6l": {
      "endId": "20250122110206-3hxztcn",
      "focusEnd": 38,
      "focusId": "20250122104749-4t996eu",
      "focusStart": 38,
      "rootId": "20250113101920-gt8wt6l",
      "scrollTop": 1659,
      "startId": "20250113105416-tb1q05f"
    },
    "20250113133511-eknhde8": {
      "endId": "20250117132059-f469251",
      "focusEnd": 9,
      "focusId": "20250117131548-eogtsdg",
      "focusStart": 9,
      "rootId": "20250113133511-eknhde8",
      "scrollTop": 0,
      "startId": "20250113133511-cd26h8b"
    },
    "20250114165856-2pzijth": {
      "endId": "20250114165942-uz1s9b0",
      "focusEnd": 0,
      "focusId": "20250114165942-uz1s9b0",
      "focusStart": 0,
      "rootId": "20250114165856-2pzijth",
      "scrollTop": 0,
      "startId": "20250114165856-d0md431"
    },
    "20250116091639-0i19xcy": {
      "endId": "20250116091723-g9g3arp",
      "focusEnd": 19,
      "focusId": "20250116091655-fnkfzhl",
      "focusStart": 19,
      "rootId": "20250116091639-0i19xcy",
      "scrollTop": 0,
      "startId": "20250116091639-6xisgeo"
    },
    "20250119160724-pqqap3s": {
      "endId": "20250119160724-zkjbesx",
      "focusEnd": 0,
      "focusId": "20250119160724-zkjbesx",
      "focusStart": 0,
      "rootId": "20250119160724-pqqap3s",
      "scrollTop": 0,
      "startId": "20250119160724-zkjbesx"
    },
    "20250120084635-klnl1ri": {
      "endId": "20250120084635-92tweyo",
      "focusEnd": 0,
      "focusId": "20250120084635-92tweyo",
      "focusStart": 0,
      "rootId": "20250120084635-klnl1ri",
      "scrollTop": 0,
      "startId": "20250120084635-92tweyo"
    },
    "20250121163247-7lt878k": {
      "endId": "20250121163355-oimszdh",
      "focusEnd": 29,
      "focusId": "20250121173807-8iwgxxm",
      "focusStart": 29,
      "rootId": "20250121163247-7lt878k",
      "scrollTop": 0,
      "startId": "20250121163247-282x83c"
    },
    "20250201094653-2ysnn1b": {
      "endId": "20250201094653-4e08mdx",
      "focusEnd": 0,
      "focusId": "20250201094653-4e08mdx",
      "focusStart": 0,
      "rootId": "20250201094653-2ysnn1b",
      "scrollTop": 0,
      "startId": "20250201094653-4e08mdx"
    },
    "20250205201851-8tq614g": {
      "endId": "20250206141650-bodpjrt",
      "focusEnd": 0,
      "focusId": "20250206141650-bodpjrt",
      "focusStart": 0,
      "rootId": "20250205201851-8tq614g",
      "scrollTop": 0,
      "startId": "20250205201851-iaj1jxb"
    },
    "20250208231124-6w0s5om": {
      "endId": "20250210115108-h06zyqk",
      "focusEnd": 1,
      "focusId": "20250210115108-h06zyqk",
      "focusStart": 1,
      "rootId": "20250208231124-6w0s5om",
      "scrollTop": 0,
      "startId": "20250208231124-bfnb9om"
    }
  },
  "local-filespaths": [
    {
      "notebookId": "20241223162646-1iyl4qg",
      "openPaths": [
        "/20250219154011-5s9h7l3.sy"
      ]
    },
    {
      "notebookId": "20250119160648-xe806cv",
      "openPaths": [
        "/20250120084635-klnl1ri.sy"
      ]
    },
    {
      "notebookId": "20250201094650-8734nzw",
      "openPaths": [
        "/20250208231124-6w0s5om.sy"
      ]
    }
  ],
  "local-searchkeys": {
    "col": "",
    "colTab": "",
    "keys": [
      "172.",
      ""
    ],
    "layout": 0,
    "layoutTab": 0,
    "replaceKeys": [],
    "row": "",
    "rowTab": ""
  }
}